{"statename":{},"distance":"0.000","elevation":"21","osmtags":{"sp_name":"Observatory","dc_name":"City of Cape Town","mn_code":"199","shape_leng":"0.07615803617","mp_name":"Cape Town","mn_type":"METRO","sp_code":"100000000","name":"Observatory","mp_code":"199037","mn_mdb_c":"CPT","objectid":"1189","shape_area":"0.0003026562","dc_mdb_c":"CPT","dc_mn_c":"199","OGR_FID":"1264","mn_name":"City of Cape Town"},"state":"Western Cape","latt":"-33.93300","city":"Cape Town","prov":"ZA","geocode":"CAPETOWN-IKOOQ","geonumber":"3396592205412","country":"South Africa","stnumber":"1","staddress":"Liesbeek Parkway","inlatt":"-33.93300","alt":{"loc":[{"staddress":"LIESBEEK WAY","stnumber":"6","postal":{},"dist":"0.109","latt":"-33.93242","city":"Cape Town","prov":"City of Cape Town","longt":"18.47495","class":{}},{"staddress":"Liesbeek Parkway","stnumber":"1","postal":"7925","dist":"0.000","latt":"-33.933","city":"Cape Town","prov":"Western Cape","longt":"18.474","class":{}}]},"timezone":"Africa/Johannesburg","region":"Cape Town, Western Cape","postal":"7925","poi":{"poilat":"-33.93401","website":"http://www.slugandlettuce.co.za/","opening_hours":"Mo-Sa 08:00-22:00; Su 08:00-16:30","smoking":"outside","name":"Slug and Lettuce","phone":"+27 21 448 7906","amenity":"pub","poilon":"18.47446","id":"4385147693","brewery":"yes","poidist":"0.120","name_en":"Slug and Lettuce"},"longt":"18.47400","remaining_credits":{},"confidence":"0.9","inlongt":"18.47400","class":{},"adminareas":{"admin10":{"level":"10","ref":"19100057","boundary":"administrative","name":"Cape Town Ward 57","type":"boundary","admin_level":"10"},"admin6":{"wikipedia":"en:City of Cape Town","wikidata":"Q1185115","name_de":"Kapstadt","ref":"CPT","name":"City of Cape Town","land_area":"administrative","admin_level":"6","name_lt":"Keiptauno miestas","level":"6","common_name":"Cape Town","boundary":"administrative","type":"boundary"},"admin12":{"sp_name":"Observatory","dc_name":"City of Cape Town","mn_code":"199","shape_leng":"0.07615803617","mp_name":"Cape Town","mn_type":"METRO","sp_code":"100000000","name":"Observatory","mp_code":"199037","mn_mdb_c":"CPT","objectid":"1189","shape_area":"0.0003026562","dc_mdb_c":"CPT","level":"12","dc_mn_c":"199","OGR_FID":"1264","mn_name":"City of Cape Town"}},"altgeocode":"ERVATZA-IKOOQ"}