{"statename":{},"distance":"0.026","elevation":"752","osmtags":{"wikipedia":"es:Medina de Rioseco","wikidata":"Q1648251","source":"BDLL25, EGRN, Instituto Geográfico Nacional","population":"5042","idee_name":"Medina de Rioseco","ine_municipio":"47086","is_in":"Valladolid, Castilla y León, Spain","is_in_region":"Castilla y León","name":"Medina de Rioseco","is_in_country":"Spain","is_in_province":"Valladolid","admin_level":"8","population_date":"2009","boundary":"administrative","type":"boundary"},"state":"Castile and León","latt":"41.88381","city":"Medina de Rioseco","prov":"ES","intersection":{"distance":"0.044","xlat":"41.883738","xlon":"-5.0457","street2":"Calle San Juan","street1":"C. San Juan"},"geocode":"TORDESILLAS-JPFNQ","geonumber":"3145301641758","country":"Spain","stnumber":"9","staddress":"CL SAN JUAN","inlatt":"41.88358","alt":{"loc":[{"staddress":"CL SAN JUAN","stnumber":"9","postal":"47800","latt":"41.88381","city":"Medina de Rioseco","prov":"Castile and León","longt":"-5.04615","class":{}},{"staddress":"San Juan","stnumber":"9","postal":{},"latt":"41.88381","city":"Medina de Rioseco","prov":"Castile and León","longt":"-5.04615","class":{}},{"staddress":"CL SAN JUAN","stnumber":"9","postal":"47800","dist":"0.026","latt":"41.88381","city":"Medina de Rioseco","prov":"Castile and León","longt":"-5.04615","class":{}},{"staddress":"CL SAN JUAN","stnumber":"11","postal":"47800","dist":"0.041","latt":"41.88393","city":"Medina de Rioseco","prov":"Castile and León","longt":"-5.04634","class":{}}]},"timezone":"Europe/Madrid","region":"Medina de Rioseco, Castile and León","postal":"47800","poi":{"poilat":"41.88315","religion":"christian","name":"Iglesia de San Pedro Martir","amenity":"place_of_worship","source_name":"Catastro de España","poilon":"-5.04562","id":"6700628416","poidist":"0.067"},"longt":"-5.04615","remaining_credits":{},"confidence":"0.9","inlongt":"-5.04619","class":{},"adminareas":{"admin6":{"wikipedia":"es:Provincia de Valladolid","source":"BDLL25, EGRN, Instituto Geográfico Nacional","is_in_region":"Castilla y León","addr_country":"ES","is_in_country_code":"ES","name_ru":"Вальядолид","name_be":"Вальядалід","boundary":"administrative","name_el":"Βαγιαδολίδ","wikidata":"Q71097","is_in_continent":"Europe","is_in_region_code":"07","is_in":"Europe, Spain, Castilla y León","name":"Valladolid","ISO3166_2":"ES-VA","name_es":"Valladolid","name_ca":"Valladolid","is_in_country":"Spain","admin_level":"6","ine_provincia":"47","level":"6","name_ar":"بلد الوليد","type":"boundary"},"admin8":{"wikipedia":"es:Medina de Rioseco","source":"BDLL25, EGRN, Instituto Geográfico Nacional","population":"5042","idee_name":"Medina de Rioseco","ine_municipio":"47086","is_in_region":"Castilla y León","is_in_province":"Valladolid","boundary":"administrative","wikidata":"Q1648251","is_in":"Valladolid, Castilla y León, Spain","name":"Medina de Rioseco","is_in_country":"Spain","admin_level":"8","level":"8","population_date":"2009","type":"boundary"}},"altgeocode":"DEMEDINA-JPFNQ"}